pinjector/__init__.py
pinjector-0.1.0.dist-info/LICENSE
pinjector-0.1.0.dist-info/METADATA
pinjector-0.1.0.dist-info/WHEEL
pinjector-0.1.0.dist-info/top_level.txt
pinjector-0.1.0.dist-info/RECORD
