Metadata-Version: 2.1
Name: pinjector
Version: 0.1.0
Summary: Dependency injection with type annotations and minimal boiler plate code for Python.
Home-page: https://github.com/davidcim/pinjector
Author: David Cimadevilla
Author-email: dev.davidcim@gmail.com
License: UNKNOWN
Platform: UNKNOWN
Classifier: Programming Language :: Python :: 3
Classifier: License :: OSI Approved :: MIT License
Classifier: Operating System :: OS Independent
Requires-Python: >=3.5
